visiopy/__init__.py
visiopy/select_assign.py
visiopy/visio_connect.py
visiopy-0.2.1.dist-info/licenses/LICENSE
visiopy-0.2.1.dist-info/METADATA
visiopy-0.2.1.dist-info/WHEEL
visiopy-0.2.1.dist-info/top_level.txt
visiopy-0.2.1.dist-info/RECORD
